README.md
setup.cfg
setup.py
image_searcher/__init__.py
image_searcher.egg-info/PKG-INFO
image_searcher.egg-info/SOURCES.txt
image_searcher.egg-info/dependency_links.txt
image_searcher.egg-info/requires.txt
image_searcher.egg-info/top_level.txt
image_searcher/api/__init__.py
image_searcher/api/flask_config.py
image_searcher/api/run_flask_command.py
image_searcher/embedders/__init__.py
image_searcher/embedders/clip_embedder.py
image_searcher/embedders/face_embedder.py
image_searcher/interfaces/__init__.py
image_searcher/interfaces/image_loader.py
image_searcher/interfaces/result_interface.py
image_searcher/interfaces/stored_embeddings.py
image_searcher/search/__init__.py
image_searcher/search/search.py