Metadata-Version: 2.1
Name: image-searcher
Version: 0.0.3
Summary: Image Searcher based on semantic query understanding for your own pictures.
Home-page: https://github.com/ManuelFay/ImageSearcher
Author: Manuel Faysse
Author-email: manuel.fay@gmail.com
License: UNKNOWN
Download-URL: https://github.com/ManuelFay/ImageSearcher/archive/refs/tags/v0.0.3.tar.gz
Keywords: search engine,image,image search,CLIP
Platform: UNKNOWN
Requires-Python: >=3.7,<4.0
Provides-Extra: face_recognition
Provides-Extra: server
